AUTHORS.rst
CONTRIBUTING.rst
HISTORY.rst
LICENSE
MANIFEST.in
README.rst
setup.cfg
setup.py
docs/Makefile
docs/authors.rst
docs/conf.py
docs/contributing.rst
docs/history.rst
docs/index.rst
docs/installation.rst
docs/make.bat
docs/readme.rst
docs/usage.rst
eurovision/__init__.py
eurovision/eurovision.py
eurovision.egg-info/PKG-INFO
eurovision.egg-info/SOURCES.txt
eurovision.egg-info/dependency_links.txt
eurovision.egg-info/not-zip-safe
eurovision.egg-info/top_level.txt
tests/__init__.py
tests/test_eurovision.py