Metadata-Version: 2.1
Name: eurovision
Version: 0.1.0
Summary: Eurovision data
Home-page: https://github.com/noeliarico/eurovision
Author: Noelia Rico
Author-email: noeliarico@uniovi.es
License: GNU General Public License v3
Keywords: eurovision
Classifier: Development Status :: 2 - Pre-Alpha
Classifier: Intended Audience :: Developers
Classifier: License :: OSI Approved :: GNU General Public License v3 (GPLv3)
Classifier: Natural Language :: English
Classifier: Programming Language :: Python :: 3
Classifier: Programming Language :: Python :: 3.6
Classifier: Programming Language :: Python :: 3.7
Classifier: Programming Language :: Python :: 3.8
Requires-Python: >=3.6
License-File: LICENSE
License-File: AUTHORS.rst
